cloudtoken_plugin/__init__.py
cloudtoken_plugin/export_credentials_awscli.py
cloudtoken_plugin.awscli_exporter-0.1.764.dist-info/LICENSE.txt
cloudtoken_plugin.awscli_exporter-0.1.764.dist-info/METADATA
cloudtoken_plugin.awscli_exporter-0.1.764.dist-info/WHEEL
cloudtoken_plugin.awscli_exporter-0.1.764.dist-info/top_level.txt
cloudtoken_plugin.awscli_exporter-0.1.764.dist-info/RECORD
